pyqchem/__init__.py
pyqchem/basis.py
pyqchem/cache.py
pyqchem/errors.py
pyqchem/file_io.py
pyqchem/plots.py
pyqchem/qc_input.py
pyqchem/qchem_core.py
pyqchem/structure.py
pyqchem/symmetry.py
pyqchem/test.py
pyqchem/units.py
pyqchem/utils.py
pyqchem/parsers/__init__.py
pyqchem/parsers/basic.py
pyqchem/parsers/parser_cis.py
pyqchem/parsers/parser_fchk.py
pyqchem/parsers/parser_frequencies.py
pyqchem/parsers/parser_irc.py
pyqchem/parsers/parser_optimization.py
pyqchem/parsers/parser_rasci.py
pyqchem/parsers/common/__init__.py
pyqchem-0.9.8.dist-info/licenses/LICENSE
pyqchem-0.9.8.dist-info/METADATA
pyqchem-0.9.8.dist-info/WHEEL
pyqchem-0.9.8.dist-info/top_level.txt
pyqchem-0.9.8.dist-info/RECORD
