Metadata-Version: 2.4
Name: pyqchem
Version: 0.9.8
Summary: Python wrapper for Q-Chem
Home-page: https://github.com/abelcarreras/PyQchem
Author: Abel Carreras
Author-email: abelcarreras83@gmail.com
Classifier: Programming Language :: Python
Classifier: License :: OSI Approved :: MIT License
License-File: LICENSE
Requires-Dist: numpy
Requires-Dist: scipy
Requires-Dist: lxml
Requires-Dist: requests
Requires-Dist: matplotlib
Requires-Dist: PyYAML
Dynamic: author
Dynamic: author-email
Dynamic: classifier
Dynamic: description
Dynamic: description-content-type
Dynamic: home-page
Dynamic: license-file
Dynamic: requires-dist
Dynamic: summary
